gitbotx/__init__.py
gitbotx/cli.py
gitbotx/repo.py
gitbotx-0.1.1.dist-info/licenses/LICENSE
gitbotx-0.1.1.dist-info/METADATA
gitbotx-0.1.1.dist-info/WHEEL
gitbotx-0.1.1.dist-info/entry_points.txt
gitbotx-0.1.1.dist-info/top_level.txt
gitbotx-0.1.1.dist-info/RECORD
