Metadata-Version: 2.4
Name: gitbotx
Version: 0.1.1
Summary: A smart CLI tool to automate git workflows and suggest commands
Home-page: https://github.com/parikshit-06/gitbotx
Author: Parikshit Sonwane
Author-email: parik.sonwane06@gmail.com
Classifier: Programming Language :: Python :: 3
Requires-Python: >=3.8
License-File: LICENSE
Dynamic: author
Dynamic: author-email
Dynamic: classifier
Dynamic: description
Dynamic: description-content-type
Dynamic: home-page
Dynamic: license-file
Dynamic: requires-python
Dynamic: summary
